http_request/__init__.py
http_request/proxy.py
syntax/__init__.py
syntax/fs.py
khala_python_utils-0.0.6.dist-info/LICENSE
khala_python_utils-0.0.6.dist-info/METADATA
khala_python_utils-0.0.6.dist-info/WHEEL
khala_python_utils-0.0.6.dist-info/RECORD
