Metadata-Version: 2.1
Name: khala-python-utils
Version: 0.0.6
Summary: @davidkhala/python-utils
Author: David Liu
Author-email: david-khala@hotmail.com
Requires-Python: >=3.11,<4.0
Classifier: Programming Language :: Python :: 3
Classifier: Programming Language :: Python :: 3.11
Requires-Dist: python-dotenv (>=1.0.0,<2.0.0)
Requires-Dist: requests (>=2)
